Vending.vhd
library ieee;
use ieee.numeric_std.all;
use ieee.std_logic_1164.all;

entity vending is 
    port (
        clk                 : in std_logic;
        Coin_in             : in std_logic_vector(1 downto 0);
        ticket              : in std_logic_vector(1 downto 0);
        Submit              : in std_logic;
        T5_out,T4_out,T15_out : out std_logic;
        value               :out integer range 0 to 100000
    );
end entity vending;

architecture Behavior of vending is

signal temp : integer range 0 to 100000 := 0;

begin 
  
    process (clk)
    begin 
     if (clk'event and clk = '1') then
        T5_out <= '0' ;
        T4_out <= '0';
        T15_out <= '0' ;
        value <= 0;
        if Submit = '1' then 
            value <= temp;
            temp <= 0;
        elsif ticket = "01" then
            if temp >= 500 then 
                temp <= temp - 500;
                T5_out <= '1';
            end if;
        elsif ticket = "10" then
            if temp >= 1500 then
                temp <= temp - 1500;
                T15_out <= '1';
            end if;
        elsif ticket = "11" then
            if temp >= 4000 then
                temp <= temp - 4000;
                T4_out <= '1';
            end if;
        elsif Coin_in = "01" then 
            temp <= temp + 500;
        elsif Coin_in = "10" then 
            temp <= temp + 1000;
        end if;
      end if ;
    end process;
end architecture;

sec_test.vhd
library ieee;
use ieee.numeric_std.all;
use ieee.std_logic_1164.all;

entity sec_test is
end entity;


architecture Behavior of sec_test is  
    component vending is
        port (
        clk                 : in std_logic;
        Coin_in             : in std_logic_vector(1 downto 0);
        ticket              : in std_logic_vector(1 downto 0);
        Submit              : in std_logic;
        T5_out,T4_out,T15_out : out std_logic;
        value               :out integer range 0 to 100000
    );      
    end component;

    signal    clk                 : std_logic := '0';
    signal    Coin_in             : std_logic_vector(1 downto 0);
    signal    ticket              : std_logic_vector(1 downto 0);
    signal    Submit              : std_logic;
    signal    T5_out,T4_out,T15_out: std_logic;
    signal    value               :integer range 0 to 100000;

begin
    uut:vending port map(
    clk => clk,
    Coin_in => Coin_in,
    ticket => ticket,
    Submit => Submit,
    T5_out => T5_out,
    T4_out => T4_out,
    T15_out => T15_out,
    value => value
);
clk <= not clk after 5 ns;

process
begin
    wait for 10 ns ;
        Coin_in <= "01";
    wait for 10 ns ;
        Coin_in <= "00";


    wait for 10 ns ;
        Coin_in <=  "01";
    wait for 10 ns ;
        Coin_in <= "00";
    

    wait for 15 ns ;
        Coin_in <= "01";
    wait for 10 ns ;
        Coin_in <= "00";


    wait for 10 ns ;
        Coin_in <= "10";
    wait for 10 ns ;
        Coin_in <= "00"; 

    

    wait for 10 ns ;
        Coin_in <= "10";
    wait for 10 ns ;
        Coin_in <= "00"; 


    wait for 10 ns ;
        Coin_in <= "10";
    wait for 10 ns ;
        Coin_in <= "00"; 


    wait for 10 ns ;
        Coin_in <= "10";
    wait for 10 ns ;
        Coin_in <= "00"; 




    wait for 10 ns ;
        ticket <= "01";
    wait for 10 ns ;
        ticket <= "00";



    wait for 10 ns ;
        ticket <= "11";
    wait for 10 ns ;
        ticket <= "00";



    wait for 10 ns ;
        Submit <= '1';
    wait for 15 ns ;
        Submit <= '0';


    wait;
    end process;
end architecture;

build/sec_test.vcd
$date
  Wed Feb 21 17:49:58 2024
$end
$version
  GHDL v0
$end
$timescale
  1 fs
$end
$scope module standard $end
$upscope $end
$scope module std_logic_1164 $end
$upscope $end
$scope module numeric_std $end
$upscope $end
$scope module sec_test $end
$var reg 1 ! clk $end
$var reg 2 " coin_in[1:0] $end
$var reg 2 # ticket[1:0] $end
$var reg 1 $ submit $end
$var reg 1 % t5_out $end
$var reg 1 & t4_out $end
$var reg 1 ' t15_out $end
$var integer 32 ( value $end
$scope module uut $end
$var reg 1 ) clk $end
$var reg 2 * coin_in[1:0] $end
$var reg 2 + ticket[1:0] $end
$var reg 1 , submit $end
$var reg 1 - t5_out $end
$var reg 1 . t4_out $end
$var reg 1 / t15_out $end
$var integer 32 0 value $end
$var integer 32 1 temp $end
$upscope $end
$upscope $end
$enddefinitions $end
#0
0!
bUU "
bUU #
U$
U%
U&
U'
b0 (
0)
bUU *
bUU +
U,
U-
U.
U/
b0 0
b0 1
#5000000
1!
0%
0&
0'
1)
0-
0.
0/
#10000000
0!
b01 "
0)
b01 *
#15000000
1!
1)
b111110100 1
#20000000
0!
b00 "
0)
b00 *
#25000000
1!
1)
#30000000
0!
b01 "
0)
b01 *
#35000000
1!
1)
b1111101000 1
#40000000
0!
b00 "
0)
b00 *
#45000000
1!
1)
#50000000
0!
0)
#55000000
1!
b01 "
1)
b01 *
#60000000
0!
0)
#65000000
1!
b00 "
1)
b00 *
b10111011100 1
#70000000
0!
0)
#75000000
1!
b10 "
1)
b10 *
#80000000
0!
0)
#85000000
1!
b00 "
1)
b00 *
b100111000100 1
#90000000
0!
0)
#95000000
1!
b10 "
1)
b10 *
#100000000
0!
0)
#105000000
1!
b00 "
1)
b00 *
b110110101100 1
#110000000
0!
0)
#115000000
1!
b10 "
1)
b10 *
#120000000
0!
0)
#125000000
1!
b00 "
1)
b00 *
b1000110010100 1
#130000000
0!
0)
#135000000
1!
b10 "
1)
b10 *
#140000000
0!
0)
#145000000
1!
b00 "
1)
b00 *
b1010101111100 1
#150000000
0!
0)
#155000000
1!
b01 #
1)
b01 +
#160000000
0!
0)
#165000000
1!
b00 #
1%
1)
b00 +
1-
b1001110001000 1
#170000000
0!
0)
#175000000
1!
b11 #
0%
1)
b11 +
0-
#180000000
0!
0)
#185000000
1!
b00 #
1&
1)
b00 +
1.
b1111101000 1
#190000000
0!
0)
#195000000
1!
1$
0&
1)
1,
0.
#200000000
0!
0)
#205000000
1!
b1111101000 (
1)
b1111101000 0
b0 1
#210000000
0!
0$
0)
0,
#215000000
1!
b0 (
1)
b0 0
